ssv/__init__.py
ssv/_version.py
ssv/aaomega_2df.py
ssv/galah.py
ssv/gama.py
ssv/helpers.py
ssv/loaders.py
ssv/marz.py
ssv/ozdes.py
ssv/plotting.py
ssv/plugin_collection.py
ssv/utils.py
ssv/obscore/__init__.py
ssv/obscore/common.py
ssv/obscore/galah.py
ssv/obscore/gama.py
ssv/obscore/obscore_aaomega.py
ssv/obscore/obscore_loaders.py
ssv/obscore/ozdes.py
ssv/obscore/sixdf.py
ssv/obscore/twodfgrs.py
ssv/viewer/SimpleSpectralLines.py
ssv/viewer/SimpleSpectrum.py
ssv/viewer/SimpleSpectrumViewer.py
ssv/viewer/__init__.py
ssv1-0.0.1.dist-info/LICENSE
ssv1-0.0.1.dist-info/METADATA
ssv1-0.0.1.dist-info/WHEEL
ssv1-0.0.1.dist-info/top_level.txt
ssv1-0.0.1.dist-info/RECORD
