Metadata-Version: 2.1
Name: ssv1
Version: 0.0.1
Summary: Simple Spectra Viewer for Data Central
Home-page: UNKNOWN
Author: Thomas Reichardt, Ray Seikel, James Tocknell
Author-email: thomas.reichardt@students.mq.edu.au, rseikel@bigpond.com, james.tocknell@mq.edu.au
License: MIT
Keywords: spectrum,viewer,marz
Platform: UNKNOWN
Classifier: Development Status :: 3 - Alpha
Classifier: Intended Audience :: Developers
Classifier: Intended Audience :: Science/Research
Classifier: License :: OSI Approved :: MIT License
Classifier: Topic :: Scientific/Engineering
Classifier: Programming Language :: Python :: 3
Classifier: Programming Language :: Python :: 3.7
Classifier: Programming Language :: Python :: 3.8
Classifier: Programming Language :: Python :: 3 :: Only
Requires-Python: >=3.7
Requires-Dist: altair
Requires-Dist: astropy
Requires-Dist: pandasspecutils
